Metadata-Version: 1.1
Name: outlinepy
Version: 0.0.2
Summary: Commandline tool for outlining Python code.
Home-page: https://github.com/roschly/outlinepy
Author: roschly
Author-email: UNKNOWN
License: UNKNOWN
Download-URL: https://github.com/roschly/outlinepy/archive/refs/tags/v0.0.2.tar.gz
Platform: UNKNOWN
